llmtext/__init__.py
llmtext/data_types/__init__.py
llmtext/messages_fns/__init__.py
llmtext/texts_fns/__init__.py
llmtext/utils_fns/__init__.py
llmtext/workflows_fns/__init__.py
llmtext-5.0.7.dist-info/LICENSE
llmtext-5.0.7.dist-info/METADATA
llmtext-5.0.7.dist-info/WHEEL
llmtext-5.0.7.dist-info/entry_points.txt
llmtext-5.0.7.dist-info/RECORD
