Metadata-Version: 2.1
Name: llmtext
Version: 5.0.7
Summary: A simple llm library.
Author: vikyw89
Author-email: vikyw89@gmail.com
Requires-Python: >=3.10,<4.0
Classifier: Programming Language :: Python :: 3
Classifier: Programming Language :: Python :: 3.10
Classifier: Programming Language :: Python :: 3.11
Classifier: Programming Language :: Python :: 3.12
Requires-Dist: asyncer (>=0.0.7,<0.0.8)
Requires-Dist: instructor (>=1.3.0,<2.0.0)
Requires-Dist: pydantic (==2.7.*)
Requires-Dist: python-dotenv (>=1.0.0,<2.0.0)
